pulumi_pagerduty/__init__.py
pulumi_pagerduty/_inputs.py
pulumi_pagerduty/_utilities.py
pulumi_pagerduty/addon.py
pulumi_pagerduty/alert_grouping_setting.py
pulumi_pagerduty/automation_actions_action.py
pulumi_pagerduty/automation_actions_action_service_association.py
pulumi_pagerduty/automation_actions_action_team_association.py
pulumi_pagerduty/automation_actions_runner.py
pulumi_pagerduty/automation_actions_runner_team_association.py
pulumi_pagerduty/business_service.py
pulumi_pagerduty/business_service_subscriber.py
pulumi_pagerduty/enablement.py
pulumi_pagerduty/escalation_policy.py
pulumi_pagerduty/event_orchestration.py
pulumi_pagerduty/event_orchestration_global.py
pulumi_pagerduty/event_orchestration_global_cache_variable.py
pulumi_pagerduty/event_orchestration_integration.py
pulumi_pagerduty/event_orchestration_router.py
pulumi_pagerduty/event_orchestration_service.py
pulumi_pagerduty/event_orchestration_service_cache_variable.py
pulumi_pagerduty/event_orchestration_unrouted.py
pulumi_pagerduty/event_rule.py
pulumi_pagerduty/extension.py
pulumi_pagerduty/extension_service_now.py
pulumi_pagerduty/get_alert_grouping_setting.py
pulumi_pagerduty/get_automation_actions_action.py
pulumi_pagerduty/get_automation_actions_runner.py
pulumi_pagerduty/get_business_service.py
pulumi_pagerduty/get_escalation_policy.py
pulumi_pagerduty/get_event_orchestration.py
pulumi_pagerduty/get_event_orchestration_global_cache_variable.py
pulumi_pagerduty/get_event_orchestration_integration.py
pulumi_pagerduty/get_event_orchestration_service_cache_variable.py
pulumi_pagerduty/get_event_orchestrations.py
pulumi_pagerduty/get_extension_schema.py
pulumi_pagerduty/get_incident_custom_field.py
pulumi_pagerduty/get_incident_type.py
pulumi_pagerduty/get_incident_type_custom_field.py
pulumi_pagerduty/get_incident_workflow.py
pulumi_pagerduty/get_jira_cloud_account_mapping.py
pulumi_pagerduty/get_license.py
pulumi_pagerduty/get_licenses.py
pulumi_pagerduty/get_priority.py
pulumi_pagerduty-4.29.9.dist-info/METADATA
pulumi_pagerduty-4.29.9.dist-info/WHEEL
pulumi_pagerduty-4.29.9.dist-info/top_level.txt
pulumi_pagerduty-4.29.9.dist-info/RECORD
